LICENSE.txt
MANIFEST.in
README.rst
setup.py
facebook_online_friend_tracker.egg-info/PKG-INFO
facebook_online_friend_tracker.egg-info/SOURCES.txt
facebook_online_friend_tracker.egg-info/dependency_links.txt
facebook_online_friend_tracker.egg-info/entry_points.txt
facebook_online_friend_tracker.egg-info/requires.txt
facebook_online_friend_tracker.egg-info/top_level.txt
src/__init__.py
src/main.py