Metadata-Version: 1.1
Name: facebook-online-friend-tracker
Version: 2.0.1
Summary: This tool tracks the number of online friends a user has on Facebook at any given time.
Home-page: https://github.com/bhamodi/facebook-online-friend-tracker
Author: Baraa Hamodi
Author-email: bhamodi@edu.uwaterloo.ca
License: MIT
Keywords: facebook online friend tracker python scraper selenium analysis optimization
Platform: UNKNOWN
Classifier: Development Status :: 4 - Beta
Classifier: Intended Audience :: Developers
Classifier: License :: OSI Approved :: MIT License
Classifier: Natural Language :: English
Classifier: Operating System :: OS Independent
Classifier: Programming Language :: Python
Classifier: Programming Language :: Python :: 2
Classifier: Programming Language :: Python :: 3
Classifier: Topic :: Internet :: Log Analysis
Classifier: Topic :: Software Development
Classifier: Topic :: Utilities
